jumpscale/clients/base.py
jumpscale/clients/docker/__init__.py
jumpscale/clients/docker/docker.py
jumpscale/clients/git/__init__.py
jumpscale/clients/git/git.py
jumpscale/clients/redis/__init__.py
jumpscale/clients/redis/redis.py
jumpscale/clients/sshclient/__init__.py
jumpscale/clients/sshclient/sshclient.py
jumpscale/clients/sshkey/__init__.py
jumpscale/clients/sshkey/sshkey.py
jumpscale/clients/zdb/__init__.py
jumpscale/clients/zdb/client.py
jumpscale/core/application/__init__.py
jumpscale/core/application/application.py
jumpscale/core/base/__init__.py
jumpscale/core/base/events.py
jumpscale/core/base/factory.py
jumpscale/core/base/fields.py
jumpscale/core/base/meta.py
jumpscale/core/base/store/__init__.py
jumpscale/core/base/store/filesystem.py
jumpscale/core/base/store/redis.py
jumpscale/core/base/store/serializers.py
jumpscale/core/base/store/whooshfts.py
jumpscale/core/config/__init__.py
jumpscale/core/config/config.py
jumpscale/core/db/__init__.py
jumpscale/core/dirs/__init__.py
jumpscale/core/dirs/dirs.py
jumpscale/core/events/__init__.py
jumpscale/core/exceptions/__init__.py
jumpscale/core/exceptions/exceptions.py
jumpscale/core/executors/__init__.py
jumpscale/core/executors/command_builder.py
jumpscale/core/executors/local.py
jumpscale/core/executors/remote.py
jumpscale/core/executors/tmux.py
jumpscale/core/logging/__init__.py
jumpscale/core/logging/logging.py
jumpscale/data/bcdb/__init__.py
jumpscale/data/bcdb/bcdb.py
jumpscale/data/bcdb/clients.py
jumpscale/data/bcdb/dumpsql.py
jumpscale/data/bcdb/flush.py
jumpscale/data/bcdb/interfaces.py
jumpscale/data/bcdb/models/__init__.py
jumpscale/data/bcdb/models/base.py
jumpscale/data/bcdb/models/db_model.py
jumpscale/data/bcdb/models/emplyee_model.py
jumpscale/data/bcdb/models/model_model.py
jumpscale/data/bcdb/models/post_model.py
jumpscale/data/bcdb/models/proj_model.py
jumpscale/data/bcdb/models/test_model.py
jumpscale/data/bcdb/models/user_model.py
jumpscale/data/cache/__init__.py
js_ng-12.0.0.dist-info/entry_points.txt
js_ng-12.0.0.dist-info/LICENSE
js_ng-12.0.0.dist-info/WHEEL
js_ng-12.0.0.dist-info/METADATA
js_ng-12.0.0.dist-info/RECORD
