Metadata-Version: 2.1
Name: js-ng
Version: 12.0.0
Summary: system automation, configuration management and RPC framework
License: MIT
Author: xmonader
Author-email: xmonader@gmail.com
Requires-Python: >=3.7,<4.0
Classifier: License :: OSI Approved :: MIT License
Classifier: Programming Language :: Python :: 3
Classifier: Programming Language :: Python :: 3.7
Classifier: Programming Language :: Python :: 3.8
Classifier: Programming Language :: Python :: 3.9
Classifier: Programming Language :: Python :: 3.10
Classifier: Programming Language :: Python :: 3.11
Requires-Dist: GitPython (>=3.0,<4.0)
Requires-Dist: Jinja2 (>=3.1.2,<4.0.0)
Requires-Dist: PyNaCl (>=1.5.0,<2.0.0)
Requires-Dist: PyYAML (>=5.1,<6.0)
Requires-Dist: Whoosh (>=2.7.4,<3.0.0)
Requires-Dist: arrow (>=0.15.7,<0.16.0)
Requires-Dist: better-exceptions (>=0.2.2,<0.3.0)
Requires-Dist: bottle (>=0.12.18,<0.13.0)
Requires-Dist: click (>=8.1.3,<9.0.0)
Requires-Dist: colorama (>=0.4.1,<0.5.0)
Requires-Dist: dill (>=0.3.0,<0.4.0)
Requires-Dist: distro (>=1.4,<2.0)
Requires-Dist: docker (>=4.2.0,<5.0.0)
Requires-Dist: fabric (>=2.4,<3.0)
Requires-Dist: faker (>=2.0,<3.0)
Requires-Dist: gevent (>=21.1.2,<22.0.0)
Requires-Dist: jedi (==0.17.2)
Requires-Dist: libtmux (>=0.8.2,<0.9.0)
Requires-Dist: loguru (>=0.3.2,<0.4.0)
Requires-Dist: msgpack (>=0.6.1,<0.7.0)
Requires-Dist: pdoc3 (>=0.10.0,<0.11.0)
Requires-Dist: prompt-toolkit (<3.0.0)
Requires-Dist: psutil (>=5.7.0,<6.0.0)
Requires-Dist: ptpython (>=2.0,<3.0)
Requires-Dist: pudb (>=2019.1,<2020.0)
Requires-Dist: pycparser (>=2.20,<3.0)
Requires-Dist: pylzma (>=0.5.0,<0.6.0)
Requires-Dist: pytoml (>=0.1.21,<0.2.0)
Requires-Dist: redis (>=3.3,<4.0)
Requires-Dist: requests (>=2.28.1,<3.0.0)
Requires-Dist: secretconf (>=0.1.2,<0.2.0)
Requires-Dist: terminaltables (>=3.1,<4.0)
Requires-Dist: watchdog (>=2.1.9,<3.0.0)
Requires-Dist: zipp (>=3.1.0,<4.0.0)
